nlp_tfidf/__init__.py
nlp_tfidf/stop_word.py
nlp_tfidf/tfidf.py
nlp_tfidf-1.6.7.dist-info/LICENSE
nlp_tfidf-1.6.7.dist-info/METADATA
nlp_tfidf-1.6.7.dist-info/WHEEL
nlp_tfidf-1.6.7.dist-info/top_level.txt
nlp_tfidf-1.6.7.dist-info/RECORD
