Metadata-Version: 2.2
Name: nlp-tfidf
Version: 1.6.7
Summary: My short description for my project.
Home-page: https://github.com/yino/nlp-tf-idf
Author: yino
Author-email: m15829090357@163.com
License: MIT
Classifier: License :: OSI Approved :: MIT License
Classifier: Programming Language :: Python
Classifier: Programming Language :: Python :: 3
Classifier: Programming Language :: Python :: 3.6
Classifier: Programming Language :: Python :: Implementation :: CPython
Classifier: Programming Language :: Python :: Implementation :: PyPy
Requires-Python: >=3.0
License-File: LICENSE
Requires-Dist: pandas
Requires-Dist: gensim
Requires-Dist: jieba
Dynamic: author
Dynamic: author-email
Dynamic: classifier
Dynamic: description
Dynamic: description-content-type
Dynamic: home-page
Dynamic: license
Dynamic: requires-dist
Dynamic: requires-python
Dynamic: summary
